code_wake_v1rest_store/__init__.py
code_wake_v1rest_store/pkg_meta.py
code_wake_v1rest_store/utils.py
code_wake_v1rest_store/v1reststore.py
code_wake_v1rest_store-0.2.1.dist-info/LICENSE
code_wake_v1rest_store-0.2.1.dist-info/METADATA
code_wake_v1rest_store-0.2.1.dist-info/WHEEL
code_wake_v1rest_store-0.2.1.dist-info/entry_points.txt
code_wake_v1rest_store-0.2.1.dist-info/top_level.txt
code_wake_v1rest_store-0.2.1.dist-info/RECORD
