Metadata-Version: 2.1
Name: code-wake-v1rest-store
Version: 0.2.1
Summary: Code Wake V1 REST API store adapter
Home-page: https://github.com/mwri/pycodewake-v1rest-store
Author: Michael Wright
Author-email: mjw@methodanalysis.com
License: UNKNOWN
Platform: UNKNOWN
Classifier: Programming Language :: Python :: 3
Classifier: License :: OSI Approved :: MIT License
Classifier: Operating System :: OS Independent
Requires-Python: >=3.6
Requires-Dist: code-wake (~=0.2.0)
Requires-Dist: requests (==2.28.0)
Provides-Extra: dev
Requires-Dist: black (==22.3.0) ; extra == 'dev'
Requires-Dist: code-wake-sql14-store (~=0.3.0) ; extra == 'dev'
Requires-Dist: code-wake-v1wsgi-service (~=0.2.0) ; extra == 'dev'
Requires-Dist: coverage (==6.2) ; extra == 'dev'
Requires-Dist: flask (==2.1.2) ; extra == 'dev'
Requires-Dist: isort (==5.10.1) ; extra == 'dev'
Requires-Dist: mypy (==0.961) ; extra == 'dev'
Requires-Dist: pytest (==7.0.1) ; extra == 'dev'
Requires-Dist: requests-flask-adapter (==0.1.0) ; extra == 'dev'
Requires-Dist: types-requests (==2.28.0) ; extra == 'dev'
